ansible_variables/__init__.py
ansible_variables/cli/__init__.py
ansible_variables/cli/variables.py
ansible_variables/utils/__init__.py
ansible_variables/utils/vars.py
ansible_variables-0.9.1.dist-info/licenses/LICENSE
ansible_variables-0.9.1.dist-info/METADATA
ansible_variables-0.9.1.dist-info/WHEEL
ansible_variables-0.9.1.dist-info/entry_points.txt
ansible_variables-0.9.1.dist-info/top_level.txt
ansible_variables-0.9.1.dist-info/RECORD
