Metadata-Version: 2.4
Name: ansible-variables
Version: 0.9.1
Summary: Keep track of Ansible host context variables
Author-email: Christoph Hille <hille721@gmail.com>
License:                     GNU GENERAL PUBLIC LICENSE
Project-URL: Homepage, https://github.com/hille721/ansible-variables
Project-URL: Documentation, https://github.com/hille721/ansible-variables/blob/main/README.md
Project-URL: Repository, https://github.com/hille721/ansible-variables.git
Project-URL: Bug Tracker, https://github.com/hille721/ansible-variables/issues
Project-URL: Changelog, https://github.com/hille721/ansible-variables/blob/master/CHANGELOG.md
Classifier: Development Status :: 5 - Production/Stable
Classifier: Environment :: Console
Classifier: Intended Audience :: Developers
Classifier: Intended Audience :: Information Technology
Classifier: Intended Audience :: System Administrators
Classifier: License :: OSI Approved :: GNU General Public License v3 or later (GPLv3+)
Classifier: Natural Language :: English
Classifier: Operating System :: POSIX
Classifier: Programming Language :: Python :: 3
Classifier: Programming Language :: Python :: 3.8
Classifier: Programming Language :: Python :: 3.9
Classifier: Programming Language :: Python :: 3.10
Classifier: Programming Language :: Python :: 3.11
Classifier: Programming Language :: Python :: 3.12
Classifier: Programming Language :: Python :: 3.13
Classifier: Programming Language :: Python :: 3 :: Only
Classifier: Topic :: System :: Installation/Setup
Classifier: Topic :: System :: Systems Administration
Classifier: Topic :: Utilities
Requires-Python: <3.14,>=3.8
License-File: LICENSE
Requires-Dist: ansible-core>=2.11.0; python_version <= "3.9"
Requires-Dist: ansible-core<8,>=2.12.0; python_version == "3.10"
Requires-Dist: ansible-core<8,>=2.14.0; python_version == "3.11"
Requires-Dist: ansible-core<8,>=2.16.0; python_version == "3.12"
Requires-Dist: ansible-core<8,>=2.18.0; python_version == "3.13"
Requires-Dist: rich
Dynamic: license-file
